MANIFEST.in
setup.py
slurpy/__init__.py
slurpy/serialize.py
slurpy.egg-info/PKG-INFO
slurpy.egg-info/SOURCES.txt
slurpy.egg-info/dependency_links.txt
slurpy.egg-info/requires.txt
slurpy.egg-info/top_level.txt
slurpy/js/slurpy.js