Metadata-Version: 1.1
Name: slurpy
Version: 0.1.6
Summary: Call python methods from javascript and viceversa
Home-page: UNKNOWN
Author: Jorge Niedbalski R.
Author-email: jnr@pyrosome.org
License: BSD
Keywords: rpc javascript js-rpc javascript-rpc call python from javascript slurpy slurpe slurp
Platform: UNKNOWN
Classifier: Development Status :: 3 - Alpha
Classifier: Intended Audience :: Developers
Classifier: Operating System :: Unix 
